setup.cfg
setup.py
exp_sdk/__init__.py
exp_sdk/api.py
exp_sdk/authenticator.py
exp_sdk/exceptions.py
exp_sdk/exp.py
exp_sdk/network.py
exp_sdk.egg-info/PKG-INFO
exp_sdk.egg-info/SOURCES.txt
exp_sdk.egg-info/dependency_links.txt
exp_sdk.egg-info/requires.txt
exp_sdk.egg-info/top_level.txt