Metadata-Version: 1.1
Name: exp-sdk
Version: 1.0.6
Summary: EXP Python SDK
Home-page: https://github.com/scalainc/exp-python2-sdk
Author: Scala
Author-email: james.dalessio@scala.com
License: MIT
Download-URL: https://github.com/scalainc/exp-python2-sdk/tarball/1.0.6
Keywords: scala,exp,sdk,signage
Platform: UNKNOWN
Classifier: Programming Language :: Python :: 2
